wikme/__init__.py
wikme/wikme.py
wikme-1.1.3.dist-info/entry_points.txt
wikme-1.1.3.dist-info/WHEEL
wikme-1.1.3.dist-info/METADATA
wikme-1.1.3.dist-info/RECORD
