Metadata-Version: 2.1
Name: wikme
Version: 1.1.3
Summary: Please refer to the documentation provided in the README.md,
Author-email: Stef Dunlap <hello@kindrobot.ca>
Requires-Dist: cmarkgfm
Project-URL: Home, https://tilde.fans
